LbCommon/CMake.py
LbCommon/ConfigFile.py
LbCommon/Env.py
LbCommon/Log.py
LbCommon/Option.py
LbCommon/Processes.py
LbCommon/Script.py
LbCommon/Temporary.py
LbCommon/__init__.py
LbCommon/tests/__init__.py
LbCommon/tests/test_script.py
LbCommon-0.0.11.dist-info/LICENSE
LbCommon-0.0.11.dist-info/METADATA
LbCommon-0.0.11.dist-info/WHEEL
LbCommon-0.0.11.dist-info/top_level.txt
LbCommon-0.0.11.dist-info/zip-safe
LbCommon-0.0.11.dist-info/RECORD
